[{"type":"dictionary","name":"KeyframeAnimationOptions","partial":false,"members":[{"type":"field","name":"id","required":false,"idlType":{"sequence":false,"generic":null,"nullable":false,"union":false,"idlType":"DOMString"},"extAttrs":[],"default":{"type":"string","value":""}}],"inheritance":"KeyframeEffectOptions","extAttrs":[]},{"type":"dictionary","name":"AnimationFilter","partial":false,"members":[{"type":"field","name":"subtree","required":false,"idlType":{"sequence":false,"generic":null,"nullable":false,"union":false,"idlType":"boolean"},"extAttrs":[],"default":{"type":"boolean","value":false}}],"inheritance":null,"extAttrs":[]},{"type":"interface","name":"Animatable","partial":false,"members":[{"type":"operation","getter":false,"setter":false,"creator":false,"deleter":false,"legacycaller":false,"static":false,"stringifier":false,"idlType":{"sequence":false,"generic":null,"nullable":false,"union":false,"idlType":"Animation"},"name":"animate","arguments":[{"optional":false,"variadic":false,"extAttrs":[],"idlType":{"sequence":false,"generic":null,"nullable":true,"union":false,"idlType":"object"},"name":"keyframes"},{"optional":true,"variadic":false,"extAttrs":[],"idlType":{"sequence":false,"generic":null,"nullable":false,"union":false,"idlType":"UnrestrictedDoubleOrKeyframeAnimationOptions"},"name":"options"}],"extAttrs":[{"name":"Func","arguments":null,"rhs":{"type":"string","value":"\"nsDocument::IsElementAnimateEnabled\""}},{"name":"Throws","arguments":null}]},{"type":"operation","getter":false,"setter":false,"creator":false,"deleter":false,"legacycaller":false,"static":false,"stringifier":false,"idlType":{"sequence":true,"generic":"sequence","nullable":false,"union":false,"idlType":{"sequence":false,"generic":null,"nullable":false,"union":false,"idlType":"Animation"}},"name":"getAnimations","arguments":[{"optional":true,"variadic":false,"extAttrs":[],"idlType":{"sequence":false,"generic":null,"nullable":false,"union":false,"idlType":"AnimationFilter"},"name":"filter"}],"extAttrs":[{"name":"Func","arguments":null,"rhs":{"type":"string","value":"\"nsDocument::IsWebAnimationsEnabled\""}}]}],"inheritance":null,"extAttrs":[{"name":"NoInterfaceObject","arguments":null}]}]
