[{"type":"interface","name":"FileReaderSync","partial":false,"members":[{"type":"operation","getter":false,"setter":false,"creator":false,"deleter":false,"legacycaller":false,"static":false,"stringifier":false,"idlType":{"sequence":false,"generic":null,"nullable":false,"union":false,"idlType":"ArrayBuffer"},"name":"readAsArrayBuffer","arguments":[{"optional":false,"variadic":false,"extAttrs":[],"idlType":{"sequence":false,"generic":null,"nullable":false,"union":false,"idlType":"Blob"},"name":"blob"}],"extAttrs":[{"name":"Throws","arguments":null}]},{"type":"operation","getter":false,"setter":false,"creator":false,"deleter":false,"legacycaller":false,"static":false,"stringifier":false,"idlType":{"sequence":false,"generic":null,"nullable":false,"union":false,"idlType":"DOMString"},"name":"readAsBinaryString","arguments":[{"optional":false,"variadic":false,"extAttrs":[],"idlType":{"sequence":false,"generic":null,"nullable":false,"union":false,"idlType":"Blob"},"name":"blob"}],"extAttrs":[{"name":"Throws","arguments":null}]},{"type":"operation","getter":false,"setter":false,"creator":false,"deleter":false,"legacycaller":false,"static":false,"stringifier":false,"idlType":{"sequence":false,"generic":null,"nullable":false,"union":false,"idlType":"DOMString"},"name":"readAsText","arguments":[{"optional":false,"variadic":false,"extAttrs":[],"idlType":{"sequence":false,"generic":null,"nullable":false,"union":false,"idlType":"Blob"},"name":"blob"},{"optional":true,"variadic":false,"extAttrs":[],"idlType":{"sequence":false,"generic":null,"nullable":false,"union":false,"idlType":"DOMString"},"name":"encoding"}],"extAttrs":[{"name":"Throws","arguments":null}]},{"type":"operation","getter":false,"setter":false,"creator":false,"deleter":false,"legacycaller":false,"static":false,"stringifier":false,"idlType":{"sequence":false,"generic":null,"nullable":false,"union":false,"idlType":"DOMString"},"name":"readAsDataURL","arguments":[{"optional":false,"variadic":false,"extAttrs":[],"idlType":{"sequence":false,"generic":null,"nullable":false,"union":false,"idlType":"Blob"},"name":"blob"}],"extAttrs":[{"name":"Throws","arguments":null}]}],"inheritance":null,"extAttrs":[{"name":"Constructor","arguments":null},{"name":"Exposed","arguments":null,"rhs":{"type":"identifier","value":"Worker"}}]}]
