[{"type":"interface","name":"NamedNodeMap","partial":false,"members":[{"type":"operation","getter":true,"setter":false,"creator":false,"deleter":false,"legacycaller":false,"static":false,"stringifier":false,"idlType":{"sequence":false,"generic":null,"nullable":true,"array":false,"union":false,"idlType":"Attr"},"name":"getNamedItem","arguments":[{"optional":false,"variadic":false,"extAttrs":[],"idlType":{"sequence":false,"generic":null,"nullable":false,"array":false,"union":false,"idlType":"DOMString"},"name":"name"}],"extAttrs":[]},{"type":"operation","getter":false,"setter":false,"creator":false,"deleter":false,"legacycaller":false,"static":false,"stringifier":false,"idlType":{"sequence":false,"generic":null,"nullable":true,"array":false,"union":false,"idlType":"Attr"},"name":"setNamedItem","arguments":[{"optional":false,"variadic":false,"extAttrs":[],"idlType":{"sequence":false,"generic":null,"nullable":false,"array":false,"union":false,"idlType":"Attr"},"name":"arg"}],"extAttrs":[{"name":"Throws","arguments":null},{"name":"BinaryName","arguments":null,"rhs":{"type":"string","value":"\"setNamedItemNS\""}}]},{"type":"operation","getter":false,"setter":false,"creator":false,"deleter":false,"legacycaller":false,"static":false,"stringifier":false,"idlType":{"sequence":false,"generic":null,"nullable":false,"array":false,"union":false,"idlType":"Attr"},"name":"removeNamedItem","arguments":[{"optional":false,"variadic":false,"extAttrs":[],"idlType":{"sequence":false,"generic":null,"nullable":false,"array":false,"union":false,"idlType":"DOMString"},"name":"name"}],"extAttrs":[{"name":"Throws","arguments":null}]},{"type":"operation","getter":true,"setter":false,"creator":false,"deleter":false,"legacycaller":false,"static":false,"stringifier":false,"idlType":{"sequence":false,"generic":null,"nullable":true,"array":false,"union":false,"idlType":"Attr"},"name":"item","arguments":[{"optional":false,"variadic":false,"extAttrs":[],"idlType":{"sequence":false,"generic":null,"nullable":false,"array":false,"union":false,"idlType":"unsigned long"},"name":"index"}],"extAttrs":[]},{"type":"attribute","static":false,"stringifier":false,"inherit":false,"readonly":true,"idlType":{"sequence":false,"generic":null,"nullable":false,"array":false,"union":false,"idlType":"unsigned long"},"name":"length","extAttrs":[]},{"type":"operation","getter":false,"setter":false,"creator":false,"deleter":false,"legacycaller":false,"static":false,"stringifier":false,"idlType":{"sequence":false,"generic":null,"nullable":true,"array":false,"union":false,"idlType":"Attr"},"name":"getNamedItemNS","arguments":[{"optional":false,"variadic":false,"extAttrs":[],"idlType":{"sequence":false,"generic":null,"nullable":true,"array":false,"union":false,"idlType":"DOMString"},"name":"namespaceURI"},{"optional":false,"variadic":false,"extAttrs":[],"idlType":{"sequence":false,"generic":null,"nullable":false,"array":false,"union":false,"idlType":"DOMString"},"name":"localName"}],"extAttrs":[]},{"type":"operation","getter":false,"setter":false,"creator":false,"deleter":false,"legacycaller":false,"static":false,"stringifier":false,"idlType":{"sequence":false,"generic":null,"nullable":true,"array":false,"union":false,"idlType":"Attr"},"name":"setNamedItemNS","arguments":[{"optional":false,"variadic":false,"extAttrs":[],"idlType":{"sequence":false,"generic":null,"nullable":false,"array":false,"union":false,"idlType":"Attr"},"name":"arg"}],"extAttrs":[{"name":"Throws","arguments":null}]},{"type":"operation","getter":false,"setter":false,"creator":false,"deleter":false,"legacycaller":false,"static":false,"stringifier":false,"idlType":{"sequence":false,"generic":null,"nullable":false,"array":false,"union":false,"idlType":"Attr"},"name":"removeNamedItemNS","arguments":[{"optional":false,"variadic":false,"extAttrs":[],"idlType":{"sequence":false,"generic":null,"nullable":true,"array":false,"union":false,"idlType":"DOMString"},"name":"namespaceURI"},{"optional":false,"variadic":false,"extAttrs":[],"idlType":{"sequence":false,"generic":null,"nullable":false,"array":false,"union":false,"idlType":"DOMString"},"name":"localName"}],"extAttrs":[{"name":"Throws","arguments":null}]}],"inheritance":null,"extAttrs":[{"name":"LegacyUnenumerableNamedProperties","arguments":null}]}]
